{
    "@context": "http://iiif.io/api/presentation/2/context.json",
    "@id": "https://makingscience.royalsociety.org/iiif/archives/PT_75_1841_25/manifest",
    "@type": "sc:Manifest",
    "label": "Conjunctival Vessels overlapping the margin of the Cornea",
    "metadata": [
        {
            "label": "Title",
            "value": "Conjunctival Vessels overlapping the margin of the Cornea"
        },
        {
            "label": "Ref no",
            "value": "PT/75/1841/25"
        }
    ],
    "otherContent": {
        "@id": "./PT_75_1841_25/tags.json",
        "@type": "sc:AnnotationList"
    },
    "sequences": [
        {
            "@id": "https://makingscience.royalsociety.org/iiif/archives/PT_75_1841_25/sequence/0",
            "@type": "sc:Sequence",
            "canvases": [
                {
                    "@id": "https://makingscience.royalsociety.org/iiif/archives/PT_75_1841_25/canvas/0",
                    "@type": "sc:Canvas",
                    "height": 2642,
                    "images": [
                        {
                            "@id": "https://makingscience.royalsociety.org/iiif/archives/PT_75_1841_25/annotation/img-0",
                            "@type": "oa:Annotation",
                            "motivation": "sc:painting",
                            "on": "https://makingscience.royalsociety.org/iiif/archives/PT_75_1841_25/canvas/0",
                            "resource": {
                                "@id": "https://dlc.services/iiif-img/rs/2/PT_75_1841_25/full/!2000,2000/0/default.jpg",
                                "@type": "dctypes:Image",
                                "height": 2642,
                                "service": {
                                    "@id": "https://dlc.services/iiif-img/rs/2/PT_75_1841_25",
                                    "height": 2642,
                                    "profile": "http://iiif.io/api/image/2/level1.json",
                                    "protocol": "http://iiif.io/api/image",
                                    "width": 2942
                                },
                                "width": 2942
                            }
                        }
                    ],
                    "otherContent": {
                        "@id": "./PT_75_1841_25/000_32369e.json",
                        "@type": "sc:AnnotationList"
                    },
                    "thumbnail": {
                        "@id": "https://dlc.services/thumbs/rs/2/PT_75_1841_25/full/full/0/default.jpg",
                        "@type": "dctypes:Image",
                        "service": {
                            "@context": "http://iiif.io/api/image/2/context.json",
                            "@id": "https://dlc.services/thumbs/rs/2/PT_75_1841_25",
                            "height": 920,
                            "profile": [
                                "http://iiif.io/api/image/2/level0.json",
                                {
                                    "formats": [
                                        "jpg"
                                    ],
                                    "qualities": [
                                        "color"
                                    ],
                                    "supports": [
                                        "sizeByWhListed"
                                    ]
                                }
                            ],
                            "sizes": [
                                {
                                    "height": 920,
                                    "width": 1024
                                },
                                {
                                    "height": 359,
                                    "width": 400
                                },
                                {
                                    "height": 180,
                                    "width": 200
                                },
                                {
                                    "height": 90,
                                    "width": 100
                                }
                            ],
                            "width": 1024
                        }
                    },
                    "width": 2942,
                    "seeAlso": {
                        "@id": "./PT_75_1841_25/000_32369e.jpg",
                        "@type": "Image",
                        "format": "image/jpg",
                        "label": "static version of image"
                    }
                }
            ],
            "label": "Sequence 0"
        }
    ],
    "thumbnail": {
        "@id": "https://dlc.services/thumbs/rs/2/PT_75_1841_25/full/full/0/default.jpg",
        "@type": "dctypes:Image",
        "service": {
            "@context": "http://iiif.io/api/image/2/context.json",
            "@id": "https://dlc.services/thumbs/rs/2/PT_75_1841_25",
            "height": 920,
            "profile": [
                "http://iiif.io/api/image/2/level0.json",
                {
                    "formats": [
                        "jpg"
                    ],
                    "qualities": [
                        "color"
                    ],
                    "supports": [
                        "sizeByWhListed"
                    ]
                }
            ],
            "sizes": [
                {
                    "height": 920,
                    "width": 1024
                },
                {
                    "height": 359,
                    "width": 400
                },
                {
                    "height": 180,
                    "width": 200
                },
                {
                    "height": 90,
                    "width": 100
                }
            ],
            "width": 1024
        }
    }
}