{
    "@context": "http://iiif.io/api/presentation/2/context.json",
    "@id": "https://makingscience.royalsociety.org/iiif/archives/PT_73_5_15/manifest",
    "@type": "sc:Manifest",
    "label": "Fossilised Ichthyosaur vertebra",
    "metadata": [
        {
            "label": "Title",
            "value": "Fossilised Ichthyosaur vertebra"
        },
        {
            "label": "Ref no",
            "value": "PT/73/5/15"
        }
    ],
    "otherContent": {
        "@id": "./PT_73_5_15/tags.json",
        "@type": "sc:AnnotationList"
    },
    "sequences": [
        {
            "@id": "https://makingscience.royalsociety.org/iiif/archives/PT_73_5_15/sequence/0",
            "@type": "sc:Sequence",
            "canvases": [
                {
                    "@id": "https://makingscience.royalsociety.org/iiif/archives/PT_73_5_15/canvas/0",
                    "@type": "sc:Canvas",
                    "height": 5623,
                    "images": [
                        {
                            "@id": "https://makingscience.royalsociety.org/iiif/archives/PT_73_5_15/annotation/img-0",
                            "@type": "oa:Annotation",
                            "motivation": "sc:painting",
                            "on": "https://makingscience.royalsociety.org/iiif/archives/PT_73_5_15/canvas/0",
                            "resource": {
                                "@id": "https://dlc.services/iiif-img/rs/2/PT_73_5_15/full/!2000,2000/0/default.jpg",
                                "@type": "dctypes:Image",
                                "height": 5623,
                                "service": {
                                    "@id": "https://dlc.services/iiif-img/rs/2/PT_73_5_15",
                                    "height": 5623,
                                    "profile": "http://iiif.io/api/image/2/level1.json",
                                    "protocol": "http://iiif.io/api/image",
                                    "width": 6968
                                },
                                "width": 6968
                            }
                        }
                    ],
                    "otherContent": {
                        "@id": "./PT_73_5_15/000_2a0d43.json",
                        "@type": "sc:AnnotationList"
                    },
                    "thumbnail": {
                        "@id": "https://dlc.services/thumbs/rs/2/PT_73_5_15/full/full/0/default.jpg",
                        "@type": "dctypes:Image",
                        "service": {
                            "@context": "http://iiif.io/api/image/2/context.json",
                            "@id": "https://dlc.services/thumbs/rs/2/PT_73_5_15",
                            "height": 826,
                            "profile": [
                                "http://iiif.io/api/image/2/level0.json",
                                {
                                    "formats": [
                                        "jpg"
                                    ],
                                    "qualities": [
                                        "color"
                                    ],
                                    "supports": [
                                        "sizeByWhListed"
                                    ]
                                }
                            ],
                            "sizes": [
                                {
                                    "height": 826,
                                    "width": 1024
                                },
                                {
                                    "height": 323,
                                    "width": 400
                                },
                                {
                                    "height": 161,
                                    "width": 200
                                },
                                {
                                    "height": 81,
                                    "width": 100
                                }
                            ],
                            "width": 1024
                        }
                    },
                    "width": 6968,
                    "seeAlso": {
                        "@id": "./PT_73_5_15/000_2a0d43.jpg",
                        "@type": "Image",
                        "format": "image/jpg",
                        "label": "static version of image"
                    }
                }
            ],
            "label": "Sequence 0"
        }
    ],
    "thumbnail": {
        "@id": "https://dlc.services/thumbs/rs/2/PT_73_5_15/full/full/0/default.jpg",
        "@type": "dctypes:Image",
        "service": {
            "@context": "http://iiif.io/api/image/2/context.json",
            "@id": "https://dlc.services/thumbs/rs/2/PT_73_5_15",
            "height": 826,
            "profile": [
                "http://iiif.io/api/image/2/level0.json",
                {
                    "formats": [
                        "jpg"
                    ],
                    "qualities": [
                        "color"
                    ],
                    "supports": [
                        "sizeByWhListed"
                    ]
                }
            ],
            "sizes": [
                {
                    "height": 826,
                    "width": 1024
                },
                {
                    "height": 323,
                    "width": 400
                },
                {
                    "height": 161,
                    "width": 200
                },
                {
                    "height": 81,
                    "width": 100
                }
            ],
            "width": 1024
        }
    }
}