{
    "@context": "http://iiif.io/api/presentation/2/context.json",
    "@id": "https://makingscience.royalsociety.org/iiif/archives/RR_2_112/canvas/ce2895/otherContent",
    "@type": "sc:AnnotationList",
    "resources": [
        {
            "@id": "https://makingscience.royalsociety.org/annotation/oa/ec7d8e69cfcce2b3625a2de26fc3acb6/d9b74790-76dc-4aa6-bcfa-68797c9f60a7",
            "@type": "oa:Annotation",
            "motivation": "oa:transcribing",
            "on": "https://makingscience.royalsociety.org/iiif/archives/RR_2_112/canvas/0",
            "resource": {
                "@type": "cnt:ContentAsText",
                "chars": "I beg leave to offer my \r\nopinion that the accom-\r\npanying paper of an \r\nof very great value & \r\noriginality & highly \r\ndeserving of publication \r\nin the Philosophical \r\nTransactions.\r\nEdward Forbes ",
                "format": "text/plain",
                "language": "en"
            }
        }
    ]
}