{
    "@context": "http://iiif.io/api/presentation/2/context.json",
    "@id": "https://makingscience.royalsociety.org/iiif/archives/CLP_5_40/manifest",
    "@type": "sc:Manifest",
    "label": "Meteorological observations from Lund, Sweden, for 1724 by an anonymous author",
    "metadata": [
        {
            "label": "Title",
            "value": "Meteorological observations from Lund, Sweden, for 1724 by an anonymous author"
        },
        {
            "label": "Ref no",
            "value": "CLP/5/40"
        }
    ],
    "otherContent": {
        "@id": "./CLP_5_40/tags.json",
        "@type": "sc:AnnotationList"
    },
    "sequences": [
        {
            "@id": "https://makingscience.royalsociety.org/iiif/archives/CLP_5_40/sequence/0",
            "@type": "sc:Sequence",
            "canvases": [
                {
                    "@id": "https://makingscience.royalsociety.org/iiif/archives/CLP_5_40/canvas/0",
                    "@type": "sc:Canvas",
                    "height": 4246,
                    "images": [
                        {
                            "@id": "https://makingscience.royalsociety.org/iiif/archives/CLP_5_40/annotation/img-0",
                            "@type": "oa:Annotation",
                            "motivation": "sc:painting",
                            "on": "https://makingscience.royalsociety.org/iiif/archives/CLP_5_40/canvas/0",
                            "resource": {
                                "@id": "https://dlc.services/iiif-img/rs/2/CLP_5_40_001/full/!2000,2000/0/default.jpg",
                                "@type": "dctypes:Image",
                                "height": 4246,
                                "service": {
                                    "@id": "https://dlc.services/iiif-img/rs/2/CLP_5_40_001",
                                    "height": 4246,
                                    "profile": "http://iiif.io/api/image/2/level1.json",
                                    "protocol": "http://iiif.io/api/image",
                                    "width": 3394
                                },
                                "width": 3394
                            }
                        }
                    ],
                    "otherContent": {
                        "@id": "./CLP_5_40/000_5cdbdb.json",
                        "@type": "sc:AnnotationList"
                    },
                    "thumbnail": {
                        "@id": "https://dlc.services/thumbs/rs/2/CLP_5_40_001/full/full/0/default.jpg",
                        "@type": "dctypes:Image",
                        "service": {
                            "@context": "http://iiif.io/api/image/2/context.json",
                            "@id": "https://dlc.services/thumbs/rs/2/CLP_5_40_001",
                            "height": 1024,
                            "profile": [
                                "http://iiif.io/api/image/2/level0.json",
                                {
                                    "formats": [
                                        "jpg"
                                    ],
                                    "qualities": [
                                        "color"
                                    ],
                                    "supports": [
                                        "sizeByWhListed"
                                    ]
                                }
                            ],
                            "sizes": [
                                {
                                    "height": 1024,
                                    "width": 819
                                },
                                {
                                    "height": 400,
                                    "width": 320
                                },
                                {
                                    "height": 200,
                                    "width": 160
                                },
                                {
                                    "height": 100,
                                    "width": 80
                                }
                            ],
                            "width": 819
                        }
                    },
                    "width": 3394,
                    "seeAlso": {
                        "@id": "./CLP_5_40/000_5cdbdb.jpg",
                        "@type": "Image",
                        "format": "image/jpg",
                        "label": "static version of image"
                    }
                },
                {
                    "@id": "https://makingscience.royalsociety.org/iiif/archives/CLP_5_40/canvas/1",
                    "@type": "sc:Canvas",
                    "height": 4403,
                    "images": [
                        {
                            "@id": "https://makingscience.royalsociety.org/iiif/archives/CLP_5_40/annotation/img-1",
                            "@type": "oa:Annotation",
                            "motivation": "sc:painting",
                            "on": "https://makingscience.royalsociety.org/iiif/archives/CLP_5_40/canvas/1",
                            "resource": {
                                "@id": "https://dlc.services/iiif-img/rs/2/CLP_5_40_002/full/!2000,2000/0/default.jpg",
                                "@type": "dctypes:Image",
                                "height": 4403,
                                "service": {
                                    "@id": "https://dlc.services/iiif-img/rs/2/CLP_5_40_002",
                                    "height": 4403,
                                    "profile": "http://iiif.io/api/image/2/level1.json",
                                    "protocol": "http://iiif.io/api/image",
                                    "width": 3553
                                },
                                "width": 3553
                            }
                        }
                    ],
                    "otherContent": {
                        "@id": "./CLP_5_40/001_a6028e.json",
                        "@type": "sc:AnnotationList"
                    },
                    "thumbnail": {
                        "@id": "https://dlc.services/thumbs/rs/2/CLP_5_40_002/full/full/0/default.jpg",
                        "@type": "dctypes:Image",
                        "service": {
                            "@context": "http://iiif.io/api/image/2/context.json",
                            "@id": "https://dlc.services/thumbs/rs/2/CLP_5_40_002",
                            "height": 1024,
                            "profile": [
                                "http://iiif.io/api/image/2/level0.json",
                                {
                                    "formats": [
                                        "jpg"
                                    ],
                                    "qualities": [
                                        "color"
                                    ],
                                    "supports": [
                                        "sizeByWhListed"
                                    ]
                                }
                            ],
                            "sizes": [
                                {
                                    "height": 1024,
                                    "width": 826
                                },
                                {
                                    "height": 400,
                                    "width": 323
                                },
                                {
                                    "height": 200,
                                    "width": 161
                                },
                                {
                                    "height": 100,
                                    "width": 81
                                }
                            ],
                            "width": 826
                        }
                    },
                    "width": 3553,
                    "seeAlso": {
                        "@id": "./CLP_5_40/001_a6028e.jpg",
                        "@type": "Image",
                        "format": "image/jpg",
                        "label": "static version of image"
                    }
                },
                {
                    "@id": "https://makingscience.royalsociety.org/iiif/archives/CLP_5_40/canvas/2",
                    "@type": "sc:Canvas",
                    "height": 4237,
                    "images": [
                        {
                            "@id": "https://makingscience.royalsociety.org/iiif/archives/CLP_5_40/annotation/img-2",
                            "@type": "oa:Annotation",
                            "motivation": "sc:painting",
                            "on": "https://makingscience.royalsociety.org/iiif/archives/CLP_5_40/canvas/2",
                            "resource": {
                                "@id": "https://dlc.services/iiif-img/rs/2/CLP_5_40_003/full/!2000,2000/0/default.jpg",
                                "@type": "dctypes:Image",
                                "height": 4237,
                                "service": {
                                    "@id": "https://dlc.services/iiif-img/rs/2/CLP_5_40_003",
                                    "height": 4237,
                                    "profile": "http://iiif.io/api/image/2/level1.json",
                                    "protocol": "http://iiif.io/api/image",
                                    "width": 3456
                                },
                                "width": 3456
                            }
                        }
                    ],
                    "otherContent": {
                        "@id": "./CLP_5_40/002_f41bea.json",
                        "@type": "sc:AnnotationList"
                    },
                    "thumbnail": {
                        "@id": "https://dlc.services/thumbs/rs/2/CLP_5_40_003/full/full/0/default.jpg",
                        "@type": "dctypes:Image",
                        "service": {
                            "@context": "http://iiif.io/api/image/2/context.json",
                            "@id": "https://dlc.services/thumbs/rs/2/CLP_5_40_003",
                            "height": 1024,
                            "profile": [
                                "http://iiif.io/api/image/2/level0.json",
                                {
                                    "formats": [
                                        "jpg"
                                    ],
                                    "qualities": [
                                        "color"
                                    ],
                                    "supports": [
                                        "sizeByWhListed"
                                    ]
                                }
                            ],
                            "sizes": [
                                {
                                    "height": 1024,
                                    "width": 835
                                },
                                {
                                    "height": 400,
                                    "width": 326
                                },
                                {
                                    "height": 200,
                                    "width": 163
                                },
                                {
                                    "height": 100,
                                    "width": 82
                                }
                            ],
                            "width": 835
                        }
                    },
                    "width": 3456,
                    "seeAlso": {
                        "@id": "./CLP_5_40/002_f41bea.jpg",
                        "@type": "Image",
                        "format": "image/jpg",
                        "label": "static version of image"
                    }
                },
                {
                    "@id": "https://makingscience.royalsociety.org/iiif/archives/CLP_5_40/canvas/3",
                    "@type": "sc:Canvas",
                    "height": 4465,
                    "images": [
                        {
                            "@id": "https://makingscience.royalsociety.org/iiif/archives/CLP_5_40/annotation/img-3",
                            "@type": "oa:Annotation",
                            "motivation": "sc:painting",
                            "on": "https://makingscience.royalsociety.org/iiif/archives/CLP_5_40/canvas/3",
                            "resource": {
                                "@id": "https://dlc.services/iiif-img/rs/2/CLP_5_40_004/full/!2000,2000/0/default.jpg",
                                "@type": "dctypes:Image",
                                "height": 4465,
                                "service": {
                                    "@id": "https://dlc.services/iiif-img/rs/2/CLP_5_40_004",
                                    "height": 4465,
                                    "profile": "http://iiif.io/api/image/2/level1.json",
                                    "protocol": "http://iiif.io/api/image",
                                    "width": 3570
                                },
                                "width": 3570
                            }
                        }
                    ],
                    "otherContent": {
                        "@id": "./CLP_5_40/003_eac9c6.json",
                        "@type": "sc:AnnotationList"
                    },
                    "thumbnail": {
                        "@id": "https://dlc.services/thumbs/rs/2/CLP_5_40_004/full/full/0/default.jpg",
                        "@type": "dctypes:Image",
                        "service": {
                            "@context": "http://iiif.io/api/image/2/context.json",
                            "@id": "https://dlc.services/thumbs/rs/2/CLP_5_40_004",
                            "height": 1024,
                            "profile": [
                                "http://iiif.io/api/image/2/level0.json",
                                {
                                    "formats": [
                                        "jpg"
                                    ],
                                    "qualities": [
                                        "color"
                                    ],
                                    "supports": [
                                        "sizeByWhListed"
                                    ]
                                }
                            ],
                            "sizes": [
                                {
                                    "height": 1024,
                                    "width": 819
                                },
                                {
                                    "height": 400,
                                    "width": 320
                                },
                                {
                                    "height": 200,
                                    "width": 160
                                },
                                {
                                    "height": 100,
                                    "width": 80
                                }
                            ],
                            "width": 819
                        }
                    },
                    "width": 3570,
                    "seeAlso": {
                        "@id": "./CLP_5_40/003_eac9c6.jpg",
                        "@type": "Image",
                        "format": "image/jpg",
                        "label": "static version of image"
                    }
                },
                {
                    "@id": "https://makingscience.royalsociety.org/iiif/archives/CLP_5_40/canvas/4",
                    "@type": "sc:Canvas",
                    "height": 4228,
                    "images": [
                        {
                            "@id": "https://makingscience.royalsociety.org/iiif/archives/CLP_5_40/annotation/img-4",
                            "@type": "oa:Annotation",
                            "motivation": "sc:painting",
                            "on": "https://makingscience.royalsociety.org/iiif/archives/CLP_5_40/canvas/4",
                            "resource": {
                                "@id": "https://dlc.services/iiif-img/rs/2/CLP_5_40_005/full/!2000,2000/0/default.jpg",
                                "@type": "dctypes:Image",
                                "height": 4228,
                                "service": {
                                    "@id": "https://dlc.services/iiif-img/rs/2/CLP_5_40_005",
                                    "height": 4228,
                                    "profile": "http://iiif.io/api/image/2/level1.json",
                                    "protocol": "http://iiif.io/api/image",
                                    "width": 3423
                                },
                                "width": 3423
                            }
                        }
                    ],
                    "otherContent": {
                        "@id": "./CLP_5_40/004_ca3200.json",
                        "@type": "sc:AnnotationList"
                    },
                    "thumbnail": {
                        "@id": "https://dlc.services/thumbs/rs/2/CLP_5_40_005/full/full/0/default.jpg",
                        "@type": "dctypes:Image",
                        "service": {
                            "@context": "http://iiif.io/api/image/2/context.json",
                            "@id": "https://dlc.services/thumbs/rs/2/CLP_5_40_005",
                            "height": 1024,
                            "profile": [
                                "http://iiif.io/api/image/2/level0.json",
                                {
                                    "formats": [
                                        "jpg"
                                    ],
                                    "qualities": [
                                        "color"
                                    ],
                                    "supports": [
                                        "sizeByWhListed"
                                    ]
                                }
                            ],
                            "sizes": [
                                {
                                    "height": 1024,
                                    "width": 829
                                },
                                {
                                    "height": 400,
                                    "width": 324
                                },
                                {
                                    "height": 200,
                                    "width": 162
                                },
                                {
                                    "height": 100,
                                    "width": 81
                                }
                            ],
                            "width": 829
                        }
                    },
                    "width": 3423,
                    "seeAlso": {
                        "@id": "./CLP_5_40/004_ca3200.jpg",
                        "@type": "Image",
                        "format": "image/jpg",
                        "label": "static version of image"
                    }
                },
                {
                    "@id": "https://makingscience.royalsociety.org/iiif/archives/CLP_5_40/canvas/5",
                    "@type": "sc:Canvas",
                    "height": 4442,
                    "images": [
                        {
                            "@id": "https://makingscience.royalsociety.org/iiif/archives/CLP_5_40/annotation/img-5",
                            "@type": "oa:Annotation",
                            "motivation": "sc:painting",
                            "on": "https://makingscience.royalsociety.org/iiif/archives/CLP_5_40/canvas/5",
                            "resource": {
                                "@id": "https://dlc.services/iiif-img/rs/2/CLP_5_40_006/full/!2000,2000/0/default.jpg",
                                "@type": "dctypes:Image",
                                "height": 4442,
                                "service": {
                                    "@id": "https://dlc.services/iiif-img/rs/2/CLP_5_40_006",
                                    "height": 4442,
                                    "profile": "http://iiif.io/api/image/2/level1.json",
                                    "protocol": "http://iiif.io/api/image",
                                    "width": 3530
                                },
                                "width": 3530
                            }
                        }
                    ],
                    "otherContent": {
                        "@id": "./CLP_5_40/005_8e07cd.json",
                        "@type": "sc:AnnotationList"
                    },
                    "thumbnail": {
                        "@id": "https://dlc.services/thumbs/rs/2/CLP_5_40_006/full/full/0/default.jpg",
                        "@type": "dctypes:Image",
                        "service": {
                            "@context": "http://iiif.io/api/image/2/context.json",
                            "@id": "https://dlc.services/thumbs/rs/2/CLP_5_40_006",
                            "height": 1024,
                            "profile": [
                                "http://iiif.io/api/image/2/level0.json",
                                {
                                    "formats": [
                                        "jpg"
                                    ],
                                    "qualities": [
                                        "color"
                                    ],
                                    "supports": [
                                        "sizeByWhListed"
                                    ]
                                }
                            ],
                            "sizes": [
                                {
                                    "height": 1024,
                                    "width": 814
                                },
                                {
                                    "height": 400,
                                    "width": 318
                                },
                                {
                                    "height": 200,
                                    "width": 159
                                },
                                {
                                    "height": 100,
                                    "width": 79
                                }
                            ],
                            "width": 814
                        }
                    },
                    "width": 3530,
                    "seeAlso": {
                        "@id": "./CLP_5_40/005_8e07cd.jpg",
                        "@type": "Image",
                        "format": "image/jpg",
                        "label": "static version of image"
                    }
                },
                {
                    "@id": "https://makingscience.royalsociety.org/iiif/archives/CLP_5_40/canvas/6",
                    "@type": "sc:Canvas",
                    "height": 4233,
                    "images": [
                        {
                            "@id": "https://makingscience.royalsociety.org/iiif/archives/CLP_5_40/annotation/img-6",
                            "@type": "oa:Annotation",
                            "motivation": "sc:painting",
                            "on": "https://makingscience.royalsociety.org/iiif/archives/CLP_5_40/canvas/6",
                            "resource": {
                                "@id": "https://dlc.services/iiif-img/rs/2/CLP_5_40_007/full/!2000,2000/0/default.jpg",
                                "@type": "dctypes:Image",
                                "height": 4233,
                                "service": {
                                    "@id": "https://dlc.services/iiif-img/rs/2/CLP_5_40_007",
                                    "height": 4233,
                                    "profile": "http://iiif.io/api/image/2/level1.json",
                                    "protocol": "http://iiif.io/api/image",
                                    "width": 3400
                                },
                                "width": 3400
                            }
                        }
                    ],
                    "otherContent": {
                        "@id": "./CLP_5_40/006_191d1f.json",
                        "@type": "sc:AnnotationList"
                    },
                    "thumbnail": {
                        "@id": "https://dlc.services/thumbs/rs/2/CLP_5_40_007/full/full/0/default.jpg",
                        "@type": "dctypes:Image",
                        "service": {
                            "@context": "http://iiif.io/api/image/2/context.json",
                            "@id": "https://dlc.services/thumbs/rs/2/CLP_5_40_007",
                            "height": 1024,
                            "profile": [
                                "http://iiif.io/api/image/2/level0.json",
                                {
                                    "formats": [
                                        "jpg"
                                    ],
                                    "qualities": [
                                        "color"
                                    ],
                                    "supports": [
                                        "sizeByWhListed"
                                    ]
                                }
                            ],
                            "sizes": [
                                {
                                    "height": 1024,
                                    "width": 822
                                },
                                {
                                    "height": 400,
                                    "width": 321
                                },
                                {
                                    "height": 200,
                                    "width": 161
                                },
                                {
                                    "height": 100,
                                    "width": 80
                                }
                            ],
                            "width": 822
                        }
                    },
                    "width": 3400,
                    "seeAlso": {
                        "@id": "./CLP_5_40/006_191d1f.jpg",
                        "@type": "Image",
                        "format": "image/jpg",
                        "label": "static version of image"
                    }
                },
                {
                    "@id": "https://makingscience.royalsociety.org/iiif/archives/CLP_5_40/canvas/7",
                    "@type": "sc:Canvas",
                    "height": 4352,
                    "images": [
                        {
                            "@id": "https://makingscience.royalsociety.org/iiif/archives/CLP_5_40/annotation/img-7",
                            "@type": "oa:Annotation",
                            "motivation": "sc:painting",
                            "on": "https://makingscience.royalsociety.org/iiif/archives/CLP_5_40/canvas/7",
                            "resource": {
                                "@id": "https://dlc.services/iiif-img/rs/2/CLP_5_40_008/full/!2000,2000/0/default.jpg",
                                "@type": "dctypes:Image",
                                "height": 4352,
                                "service": {
                                    "@id": "https://dlc.services/iiif-img/rs/2/CLP_5_40_008",
                                    "height": 4352,
                                    "profile": "http://iiif.io/api/image/2/level1.json",
                                    "protocol": "http://iiif.io/api/image",
                                    "width": 3462
                                },
                                "width": 3462
                            }
                        }
                    ],
                    "otherContent": {
                        "@id": "./CLP_5_40/007_e0f794.json",
                        "@type": "sc:AnnotationList"
                    },
                    "thumbnail": {
                        "@id": "https://dlc.services/thumbs/rs/2/CLP_5_40_008/full/full/0/default.jpg",
                        "@type": "dctypes:Image",
                        "service": {
                            "@context": "http://iiif.io/api/image/2/context.json",
                            "@id": "https://dlc.services/thumbs/rs/2/CLP_5_40_008",
                            "height": 1024,
                            "profile": [
                                "http://iiif.io/api/image/2/level0.json",
                                {
                                    "formats": [
                                        "jpg"
                                    ],
                                    "qualities": [
                                        "color"
                                    ],
                                    "supports": [
                                        "sizeByWhListed"
                                    ]
                                }
                            ],
                            "sizes": [
                                {
                                    "height": 1024,
                                    "width": 815
                                },
                                {
                                    "height": 400,
                                    "width": 318
                                },
                                {
                                    "height": 200,
                                    "width": 159
                                },
                                {
                                    "height": 100,
                                    "width": 80
                                }
                            ],
                            "width": 815
                        }
                    },
                    "width": 3462,
                    "seeAlso": {
                        "@id": "./CLP_5_40/007_e0f794.jpg",
                        "@type": "Image",
                        "format": "image/jpg",
                        "label": "static version of image"
                    }
                }
            ],
            "label": "Sequence 0"
        }
    ],
    "thumbnail": {
        "@id": "https://dlc.services/thumbs/rs/2/CLP_5_40_001/full/full/0/default.jpg",
        "@type": "dctypes:Image",
        "service": {
            "@context": "http://iiif.io/api/image/2/context.json",
            "@id": "https://dlc.services/thumbs/rs/2/CLP_5_40_001",
            "height": 1024,
            "profile": [
                "http://iiif.io/api/image/2/level0.json",
                {
                    "formats": [
                        "jpg"
                    ],
                    "qualities": [
                        "color"
                    ],
                    "supports": [
                        "sizeByWhListed"
                    ]
                }
            ],
            "sizes": [
                {
                    "height": 1024,
                    "width": 819
                },
                {
                    "height": 400,
                    "width": 320
                },
                {
                    "height": 200,
                    "width": 160
                },
                {
                    "height": 100,
                    "width": 80
                }
            ],
            "width": 819
        }
    }
}