{
    "@context": "http://iiif.io/api/presentation/2/context.json",
    "@id": "https://makingscience.royalsociety.org/iiif/archives/RR_3_183/otherContent",
    "@type": "sc:AnnotationList",
    "resources": [
        {
            "@id": "https://makingscience.royalsociety.org/annotation/oa/b067a9a5ff5a505d91623a1970e3e7bd/ad881ea0-2fbc-4496-aa15-a9971588ea55",
            "@type": "oa:Annotation",
            "motivation": "oa:tagging",
            "on": "https://makingscience.royalsociety.org/iiif/archives/RR_3_183/manifest",
            "resource": [
                {
                    "@id": "http://id.worldcat.org/fast/13195",
                    "@type": "oa:SemanticTag",
                    "foaf:page": "https://makingscience.royalsociety.org/s/rs/keywords/fst00013195"
                },
                {
                    "@type": [
                        "oa:Tag",
                        "cnt:ContentAsText"
                    ],
                    "chars": "Lubbock, John, Sir, 1834-1913"
                }
            ]
        },
        {
            "@id": "https://makingscience.royalsociety.org/annotation/oa/b067a9a5ff5a505d91623a1970e3e7bd/b92da197-6ca9-478b-840b-995d55054a62",
            "@type": "oa:Annotation",
            "motivation": "oa:tagging",
            "on": "https://makingscience.royalsociety.org/iiif/archives/RR_3_183/manifest",
            "resource": [
                {
                    "@id": "http://id.worldcat.org/fast/13195",
                    "@type": "oa:SemanticTag",
                    "foaf:page": "https://makingscience.royalsociety.org/s/rs/keywords/fst00013195"
                },
                {
                    "@type": [
                        "oa:Tag",
                        "cnt:ContentAsText"
                    ],
                    "chars": "Lubbock, John, Sir, 1834-1913"
                }
            ]
        },
        {
            "@id": "https://makingscience.royalsociety.org/annotation/oa/b067a9a5ff5a505d91623a1970e3e7bd/96354fe7-65f2-40c6-8819-67eff61291ca",
            "@type": "oa:Annotation",
            "motivation": "oa:tagging",
            "on": "https://makingscience.royalsociety.org/iiif/archives/RR_3_183/manifest",
            "resource": [
                {
                    "@id": "http://id.worldcat.org/fast/41472",
                    "@type": "oa:SemanticTag",
                    "foaf:page": "https://makingscience.royalsociety.org/s/rs/keywords/fst00041472"
                },
                {
                    "@type": [
                        "oa:Tag",
                        "cnt:ContentAsText"
                    ],
                    "chars": "Huxley, Thomas Henry, 1825-1895"
                }
            ]
        },
        {
            "@id": "https://makingscience.royalsociety.org/annotation/oa/b067a9a5ff5a505d91623a1970e3e7bd/5b32f727-ae24-4f08-b3eb-71508a7cd1d0",
            "@type": "oa:Annotation",
            "motivation": "oa:tagging",
            "on": "https://makingscience.royalsociety.org/iiif/archives/RR_3_183/manifest",
            "resource": [
                {
                    "@id": "http://id.worldcat.org/fast/41472",
                    "@type": "oa:SemanticTag",
                    "foaf:page": "https://makingscience.royalsociety.org/s/rs/keywords/fst00041472"
                },
                {
                    "@type": [
                        "oa:Tag",
                        "cnt:ContentAsText"
                    ],
                    "chars": "Huxley, Thomas Henry, 1825-1895"
                }
            ]
        },
        {
            "@id": "https://makingscience.royalsociety.org/annotation/oa/b067a9a5ff5a505d91623a1970e3e7bd/478a81ca-eb93-4b73-bce2-d2df6e568fe3",
            "@type": "oa:Annotation",
            "motivation": "oa:tagging",
            "on": "https://makingscience.royalsociety.org/iiif/archives/RR_3_183/manifest",
            "resource": [
                {
                    "@id": "http://id.worldcat.org/fast/884461",
                    "@type": "oa:SemanticTag",
                    "foaf:page": "https://makingscience.royalsociety.org/s/rs/keywords/fst00884461"
                },
                {
                    "@type": [
                        "oa:Tag",
                        "cnt:ContentAsText"
                    ],
                    "chars": "Crustacea--Physiology"
                }
            ]
        },
        {
            "@id": "https://makingscience.royalsociety.org/annotation/oa/b067a9a5ff5a505d91623a1970e3e7bd/21893543-2ba9-4dfc-bb19-36a21b1108fa",
            "@type": "oa:Annotation",
            "motivation": "oa:tagging",
            "on": "https://makingscience.royalsociety.org/iiif/archives/RR_3_183/manifest",
            "resource": [
                {
                    "@id": "http://id.worldcat.org/fast/884461",
                    "@type": "oa:SemanticTag",
                    "foaf:page": "https://makingscience.royalsociety.org/s/rs/keywords/fst00884461"
                },
                {
                    "@type": [
                        "oa:Tag",
                        "cnt:ContentAsText"
                    ],
                    "chars": "Crustacea--Physiology"
                }
            ]
        }
    ]
}