{
    "@context": "http://iiif.io/api/presentation/2/context.json",
    "@id": "https://makingscience.royalsociety.org/iiif/archives/AP_63_3/canvas/42bd7f/otherContent",
    "@type": "sc:AnnotationList",
    "resources": [
        {
            "@id": "https://makingscience.royalsociety.org/annotation/oa/8b5b842ded2c1d63fe7b0dafc7573269/668ae691-2368-42d9-b0f0-3accbf4dde3c",
            "@type": "oa:Annotation",
            "motivation": "oa:transcribing",
            "on": "https://makingscience.royalsociety.org/iiif/archives/AP_63_3/canvas/15",
            "resource": {
                "@type": "cnt:ContentAsText",
                "chars": "I shall name it <u>tractus externus <\\u>. <s>From <\\s> [The \r\n<u>tractus internus <\\u> is made up of bundles cut cross-wise &\r\nobliquely. They are firm dense <s>bundles <\\s> bands wh: have a \r\npeculiar glistening appearance in a clarified prepar-\r\nation. Below it receives a fasciculus <s>bundle <\\s> of considerable \r\nsize from the gyrus rectus, and above many fibres\r\nenter it from the first & second frontal convolutions.\r\nBy far the greater supply of fibres is evidently derived \r\nfrom the latter source. This <u>tractus internus <\\u> becomes \r\nfurther back the <u>corpus callosum <\\u>. The <u>tractus medius <\\u>\r\nas will be seen from <s>the di Figures figure 2<\\s> Fig 2.\r\ncommences a little above the <u>tractus internus <\\u>: it runs \r\ndown for a considerable distance, and ends in a \r\nfree extremity. It tapers off insensibly at each end.\r\nFurther description will be necessary to explain what it is.\r\nThe <u>tractus internus <\\u> is made up of an upper or perpendicular \r\n<s>pe <\\s> and of a lower or <s>curved <\\s> almost horizontal <s>oblique <\\s> (e.e.e) Its fibres <s>are <\\s> pass <s>a<\\s> somewhat \r\nobliquely backwards, & consequently in a perpendicular section are cut not exactly \r\ntransversely <s>across <\\>, but very nearly so. The <s>obl curved <\\s> horizontal part below \r\n<s>derives its fibres <\\s> appears to arise from the gyrus rectus (Fig 2) more externally \r\nthan the fasciculus above described <s>those of the tra <\\s> going to the tractus internus; & from \r\nthis they curve upwards for some distance, and then\r\nare cut across evidently <s>from <\\s> in turning backwards. The <u>tractus \r\nexternus <\\u> <s>forms <\\s> becomes converted <s>into <\\s> further back into the future inner & outer capsules.\r\n[Figure 3. <s>three <\\s> is a drawing of a section made through the \r\n(stet:) tip of the genu of the corpus callosum. Above <s>& laterally externally below <\\s>\r\nare the 1st 2nd & 3d frontal convolutions while below ",
                "format": "text/plain",
                "language": "en"
            }
        }
    ]
}