{
    "@context": "http://iiif.io/api/presentation/2/context.json",
    "@id": "https://makingscience.royalsociety.org/iiif/archives/PT_56_8/canvas/1b4694/otherContent",
    "@type": "sc:AnnotationList",
    "resources": [
        {
            "@id": "https://makingscience.royalsociety.org/annotation/oa/85be01d40bac10eb24dbffc5c165ab50/22fb5c86-41b0-43e9-9738-ad290b44d569",
            "@type": "oa:Annotation",
            "motivation": "oa:transcribing",
            "on": "https://makingscience.royalsociety.org/iiif/archives/PT_56_8/canvas/23",
            "resource": {
                "@type": "cnt:ContentAsText",
                "chars": "disarranging them, or disturbing their position \r\nby manipulation. Secondly, because the \r\nmaterial of which they are composed is so \r\ndissimilar in appearance to that forming \r\nthe adjacent tissue, & so characteristic that \r\nit cannot be confounded with the structures \r\nin their immediate vicinity. Thirdly, because \r\nat one view in a favourable specimen, \r\nhooklets can be seen in every stage of their \r\nformation, from the first grouping together \r\nof the masses of formative particles to the \r\nblending of them into perfect organs, & \r\nlastly, because it is not as if a mere \r\nthread of tissue were formed amongst \r\nother thread somewhat different in ap=\r\npearance, as a fibre of elastic tissue for in=\r\nstance in a mass of connective sub-\r\nstance, but the part which is here examined is a perfect organ, & one, too \r\nwhich possesses a regular arrangement \r\nof parts connected together with order & \r\nremarkable regularity. So that under \r\nsuch circumstances, if these organs had \r\nbeen preceded by nucleated cells & these \r\ncells had been transformed into hooklets, \r\nneither these cells, nor their several stages \r\nof transformation could have escaped \r\ndetection.\r\nThe parts next to be noticed are the suckers. \r\nIndications of these are visible as soon as the \r\nhooklets. They appear as four circular spaces \r\npresenting a granular aspect about the \r\nsize of perfectly formed suckers. The two sets \r\nof fibres ",
                "format": "text/plain",
                "language": "en"
            }
        }
    ]
}