{
    "@context": "http://iiif.io/api/presentation/2/context.json",
    "@id": "https://makingscience.royalsociety.org/iiif/archives/AP_27_6/canvas/9099b4/otherContent",
    "@type": "sc:AnnotationList",
    "resources": [
        {
            "@id": "https://makingscience.royalsociety.org/annotation/oa/55313887b3d5cb152e5549b9365b8a13/7e56d37e-82b8-4576-9705-d7c8a472b708",
            "@type": "oa:Annotation",
            "motivation": "oa:transcribing",
            "on": "https://makingscience.royalsociety.org/iiif/archives/AP_27_6/canvas/9",
            "resource": {
                "@type": "cnt:ContentAsText",
                "chars": "Military 1844 Department \r\nNo 3\r\nLetter from the Superintendent \r\nMagnetic Observatory at Madras \r\nTo the Secretary to Government \r\n10th January 1844.\r\nWith an Enclosure \r\nReferred to in Military Letter \r\nto England dated 26 March \r\n1844 No. 16 Para 1.\r\nReports the result of his \r\njourney to the South for the \r\npurpose of observing the \r\nSolar eclipse on the 21st\r\nDecember 1843 he has taken \r\nthe opportunity of making \r\nobservations of the Dip \r\nand Horizontal Intensity \r\nat certain places on hi \r\nreturn.\r\nRecd via Southampton \r\n11th May 1844",
                "format": "text/plain",
                "language": "en"
            }
        }
    ]
}