{
    "@context": "http://iiif.io/api/presentation/2/context.json",
    "@id": "https://makingscience.royalsociety.org/iiif/archives/AP_27_6/canvas/6d659b/otherContent",
    "@type": "sc:AnnotationList",
    "resources": [
        {
            "@id": "https://makingscience.royalsociety.org/annotation/oa/c6a867b88e3d270c065af4fa7cbdc638/ebceada3-081a-4b97-9c76-d1692b934df8",
            "@type": "oa:Annotation",
            "motivation": "oa:transcribing",
            "on": "https://makingscience.royalsociety.org/iiif/archives/AP_27_6/canvas/14",
            "resource": {
                "@type": "cnt:ContentAsText",
                "chars": "valuable on such an occasion, that I may \r\nbe allowed the Assistance of Lieutenant Ludlow \r\nwho has expressed his readiness to take part \r\nin the observation. I have the honor further \r\nto request that the hire of a Bullock Bandy \r\nto carry the instruments, together with our \r\ntravelling expenses may be allowed.\r\nI have the honor to be, &c\r\nSigned J. G. Taylor \r\nH. C. Astronomer \r\nMadras Observatory \r\nDecember 1843.\r\n1 Resolved that the \r\nHonorable Company\u2019s Astronomer be \r\npermitted to proceed on duty to Tranquebar \r\nand that he be supplied by the Com-\r\nmissariat with a Bullock Bandy for \r\nthe conveyance of his Instruments.\r\n2 Resolved that Lieutenant \r\nLudlow be requested, thro\u2019 the Military \r\nDepartment ",
                "format": "text/plain",
                "language": "en"
            }
        }
    ]
}