{
    "@context": "http://iiif.io/api/presentation/2/context.json",
    "@id": "https://makingscience.royalsociety.org/iiif/archives/AP_23_19/canvas/c27d6b/otherContent",
    "@type": "sc:AnnotationList",
    "resources": [
        {
            "@id": "https://makingscience.royalsociety.org/annotation/oa/bfe8e1beebc3cc31bc3525435285e2ff/549e2b52-9f45-4f95-96b3-791627c819b7",
            "@type": "oa:Annotation",
            "motivation": "oa:transcribing",
            "on": "https://makingscience.royalsociety.org/iiif/archives/AP_23_19/canvas/30",
            "resource": {
                "@type": "cnt:ContentAsText",
                "chars": "great improvements I have no manner \r\nof doubt: but even in its present state \r\nI believe it will be found capable of many \r\nuseful and important applications besides \r\nthose of which I have given a short account \r\nin the preceding pages -",
                "format": "text/plain",
                "language": "en"
            }
        }
    ]
}