{
    "@context": "http://iiif.io/api/presentation/2/context.json",
    "@id": "https://makingscience.royalsociety.org/iiif/archives/PT_73_8_23/otherContent",
    "@type": "sc:AnnotationList",
    "resources": [
        {
            "@id": "https://makingscience.royalsociety.org/annotation/oa/79a4d09c31d5fda5fcd761c008f6730f/481b8afd-5810-46e4-94a5-b77142308bad",
            "@type": "oa:Annotation",
            "motivation": "oa:tagging",
            "on": "https://makingscience.royalsociety.org/iiif/archives/PT_73_8_23/manifest",
            "resource": [
                {
                    "@id": "http://id.worldcat.org/fast/899387",
                    "@type": "oa:SemanticTag",
                    "foaf:page": "https://makingscience.royalsociety.org/s/rs/keywords/fst00899387"
                },
                {
                    "@type": [
                        "oa:Tag",
                        "cnt:ContentAsText"
                    ],
                    "chars": "Dugong"
                }
            ]
        }
    ]
}